cstehelloworld.py
cste_helloworld-0.0.1.dist-info/LICENSE.txt
cste_helloworld-0.0.1.dist-info/METADATA
cste_helloworld-0.0.1.dist-info/WHEEL
cste_helloworld-0.0.1.dist-info/top_level.txt
cste_helloworld-0.0.1.dist-info/RECORD
